local_qwen3b_part008/__init__.py
local_qwen3b_part008/qwen2.5-3b-instruct-q5_k_m.gguf.part_008
local_qwen3b_part008-0.0.1.dist-info/METADATA
local_qwen3b_part008-0.0.1.dist-info/WHEEL
local_qwen3b_part008-0.0.1.dist-info/top_level.txt
local_qwen3b_part008-0.0.1.dist-info/RECORD
